schnapsen/__init__.py
schnapsen/deck.py
schnapsen/game.py
schnapsen/py.typed
schnapsen/bots/__init__.py
schnapsen/bots/alphabeta.py
schnapsen/bots/bully_bot.py
schnapsen/bots/example_bot.py
schnapsen/bots/minimax.py
schnapsen/bots/ml_bot.py
schnapsen/bots/rand.py
schnapsen/bots/rdeep.py
schnapsen/bots/gui/__init__.py
schnapsen/bots/gui/guibot.py
schnapsen/bots/gui/template/gamechooser.html
schnapsen/bots/gui/template/index_interactive.html
schnapsen-0.0.5.dist-info/LICENSE
schnapsen-0.0.5.dist-info/METADATA
schnapsen-0.0.5.dist-info/WHEEL
schnapsen-0.0.5.dist-info/entry_points.txt
schnapsen-0.0.5.dist-info/top_level.txt
schnapsen-0.0.5.dist-info/RECORD
