Metadata-Version: 2.1
Name: schnapsen
Version: 0.0.5
Summary: A platform for coding and running card playing bots
Home-page: https://github.com/intelligent-systems-course/
Maintainer: Michael Cochez
Maintainer-email: nospam@nospam.com
Project-URL: Bug Tracker, https://github.com/intelligent-systems-course/
Classifier: Programming Language :: Python :: 3
Classifier: License :: OSI Approved :: GNU General Public License v3 or later (GPLv3+)
Classifier: Operating System :: OS Independent
Classifier: Development Status :: 1 - Planning
Classifier: Intended Audience :: Education
Classifier: Topic :: Games/Entertainment
Requires-Python: >=3.10
License-File: LICENSE
Requires-Dist: class_resolver>=0.0.10
Requires-Dist: click==8.1.8
Requires-Dist: scikit-learn==1.6.0
Requires-Dist: joblib==1.4.2
Requires-Dist: flask==2.3.3
Requires-Dist: Werkzeug==3.0.1
Provides-Extra: test
Requires-Dist: flake8; extra == "test"
Requires-Dist: mypy; extra == "test"
Requires-Dist: pytest; extra == "test"
Requires-Dist: unittest-templates; extra == "test"
Provides-Extra: dev
Requires-Dist: ipykernel; extra == "dev"
Provides-Extra: doc
Requires-Dist: pdoc; extra == "doc"
